{"transactionID":"","timestamp":"2025-06-22T13:20:00.5356492-04:00","requestStatus":"Success","resultIndicator":"EntityMatchFound","entitySearchResultList":[{"entityName":"A & Q AUTO CENTER, INC.","dosID":"3624600","initialFilingDate":"2008-01-30T00:00:00","county":"Westchester","nameType":"ACTUAL","assumedNameID":"","nonQualifiedID":"","assumedName":"","entityType":"DOMESTIC BUSINESS CORPORATION","entityStatus":"Active","jurisdiction":"New York, United States","entityTypeCategory":"CORPORATION"},{"entityName":"A & Q AUTO REPAIRS, INC.","dosID":"3490123","initialFilingDate":"2007-03-15T00:00:00","county":"Kings","nameType":"ACTUAL","assumedNameID":"","nonQualifiedID":"","assumedName":"","entityType":"DOMESTIC BUSINESS CORPORATION","entityStatus":"Inactive","jurisdiction":"New York, United States","entityTypeCategory":"CORPORATION"},{"entityName":"A.L.M.Q. AUTO INC.","dosID":"1164070","initialFilingDate":"1987-04-20T00:00:00","county":"Suffolk","nameType":"ACTUAL","assumedNameID":"","nonQualifiedID":"","assumedName":"","entityType":"DOMESTIC BUSINESS CORPORATION","entityStatus":"Inactive","jurisdiction":"New York, United States","entityTypeCategory":"CORPORATION"},{"entityName":"B & Q AUTO SALES INC.","dosID":"1402128","initialFilingDate":"1989-11-22T00:00:00","county":"Queens","nameType":"ACTUAL","assumedNameID":"","nonQualifiedID":"","assumedName":"","entityType":"DOMESTIC BUSINESS CORPORATION","entityStatus":"Inactive","jurisdiction":"New York, United States","entityTypeCategory":"CORPORATION"},{"entityName":"B. Q. AUTO WHOLESALERS, INC.","dosID":"300121","initialFilingDate":"1970-12-24T00:00:00","county":"Queens","nameType":"ACTUAL","assumedNameID":"","nonQualifiedID":"","assumedName":"","entityType":"DOMESTIC BUSINESS CORPORATION","entityStatus":"Inactive","jurisdiction":"New York, United States","entityTypeCategory":"CORPORATION"},{"entityName":"CAPITAL Q AUTO REPAIRS INC.","dosID":"1571580","initialFilingDate":"1991-08-27T00:00:00","county":"New York","nameType":"ACTUAL","assumedNameID":"","nonQualifiedID":"","assumedName":"","entityType":"DOMESTIC BUSINESS CORPORATION","entityStatus":"Inactive","jurisdiction":"New York, United States","entityTypeCategory":"CORPORATION"},{"entityName":"EAR Q OF AUBURN, INC.","dosID":"2447277","initialFilingDate":"1999-12-07T00:00:00","county":"Cayuga","nameType":"ACTUAL","assumedNameID":"","nonQualifiedID":"","assumedName":"","entityType":"DOMESTIC BUSINESS CORPORATION","entityStatus":"Active","jurisdiction":"New York, United States","entityTypeCategory":"CORPORATION"},{"entityName":"H Q AUTO SALES INC.","dosID":"3320428","initialFilingDate":"2006-02-14T00:00:00","county":"Queens","nameType":"ACTUAL","assumedNameID":"","nonQualifiedID":"","assumedName":"","entityType":"DOMESTIC BUSINESS CORPORATION","entityStatus":"Active","jurisdiction":"New York, United States","entityTypeCategory":"CORPORATION"},{"entityName":"H&Q AUTO PARTS WHOLESALE INC","dosID":"5337967","initialFilingDate":"2018-05-09T00:00:00","county":"Kings","nameType":"ACTUAL","assumedNameID":"","nonQualifiedID":"","assumedName":"","entityType":"DOMESTIC BUSINESS CORPORATION","entityStatus":"Inactive","jurisdiction":"New York, United States","entityTypeCategory":"CORPORATION"},{"entityName":"HI-Q AUDIO, INC.","dosID":"1935738","initialFilingDate":"1995-06-30T00:00:00","county":"Monroe","nameType":"ACTUAL","assumedNameID":"","nonQualifiedID":"","assumedName":"","entityType":"DOMESTIC BUSINESS CORPORATION","entityStatus":"Inactive","jurisdiction":"New York, United States","entityTypeCategory":"CORPORATION"},{"entityName":"HIGH-Q AUTO INC.","dosID":"2077594","initialFilingDate":"1996-10-23T00:00:00","county":"Kings","nameType":"ACTUAL","assumedNameID":"","nonQualifiedID":"","assumedName":"","entityType":"DOMESTIC BUSINESS CORPORATION","entityStatus":"Inactive","jurisdiction":"New York, United States","entityTypeCategory":"CORPORATION"},{"entityName":"J & Q AUTO NY INC","dosID":"5372480","initialFilingDate":"2018-07-09T00:00:00","county":"Queens","nameType":"ACTUAL","assumedNameID":"","nonQualifiedID":"","assumedName":"","entityType":"DOMESTIC BUSINESS CORPORATION","entityStatus":"Active","jurisdiction":"New York, United States","entityTypeCategory":"CORPORATION"},{"entityName":"JEAY SINDH QAUMI MAHAZ INC","dosID":"5254162","initialFilingDate":"2017-12-21T00:00:00","county":"Queens","nameType":"ACTUAL","assumedNameID":"","nonQualifiedID":"","assumedName":"","entityType":"DOMESTIC NOT-FOR-PROFIT CORPORATION","entityStatus":"Active","jurisdiction":"New York, United States","entityTypeCategory":"CORPORATION"},{"entityName":"L & Q AUTO REPAIR II INC.","dosID":"4490777","initialFilingDate":"2013-11-21T00:00:00","county":"Westchester","nameType":"ACTUAL","assumedNameID":"","nonQualifiedID":"","assumedName":"","entityType":"DOMESTIC BUSINESS CORPORATION","entityStatus":"Active","jurisdiction":"New York, United States","entityTypeCategory":"CORPORATION"},{"entityName":"L & Q AUTO REPAIR, INC.","dosID":"4432259","initialFilingDate":"2013-07-17T00:00:00","county":"Westchester","nameType":"ACTUAL","assumedNameID":"","nonQualifiedID":"","assumedName":"","entityType":"DOMESTIC BUSINESS CORPORATION","entityStatus":"Active","jurisdiction":"New York, United States","entityTypeCategory":"CORPORATION"},{"entityName":"L. Q. AUTO BODY SERVICE INC.","dosID":"362018","initialFilingDate":"1975-02-05T00:00:00","county":"Westchester","nameType":"ACTUAL","assumedNameID":"","nonQualifiedID":"","assumedName":"","entityType":"DOMESTIC BUSINESS CORPORATION","entityStatus":"Inactive","jurisdiction":"New York, United States","entityTypeCategory":"CORPORATION"},{"entityName":"M & Q AUTO REPAIR INC.","dosID":"3957522","initialFilingDate":"2010-06-03T00:00:00","county":"Westchester","nameType":"ACTUAL","assumedNameID":"","nonQualifiedID":"","assumedName":"","entityType":"DOMESTIC BUSINESS CORPORATION","entityStatus":"Inactive","jurisdiction":"New York, United States","entityTypeCategory":"CORPORATION"},{"entityName":"MCDONALD HI-Q AUTO REPAIRS & COLLISION INC.","dosID":"2615665","initialFilingDate":"2001-03-13T00:00:00","county":"Kings","nameType":"ACTUAL","assumedNameID":"","nonQualifiedID":"","assumedName":"","entityType":"DOMESTIC BUSINESS CORPORATION","entityStatus":"Active","jurisdiction":"New York, United States","entityTypeCategory":"CORPORATION"},{"entityName":"MOLLA & QAUSH CONSTRUCTION CORP.","dosID":"2333593","initialFilingDate":"1999-01-11T00:00:00","county":"Bronx","nameType":"ACTUAL","assumedNameID":"","nonQualifiedID":"","assumedName":"","entityType":"DOMESTIC BUSINESS CORPORATION","entityStatus":"Inactive","jurisdiction":"New York, United States","entityTypeCategory":"CORPORATION"},{"entityName":"P C Q AUTOMOBILE TRANSPORT, INC.","dosID":"919652","initialFilingDate":"1984-05-29T00:00:00","county":"Queens","nameType":"ACTUAL","assumedNameID":"","nonQualifiedID":"","assumedName":"","entityType":"DOMESTIC BUSINESS CORPORATION","entityStatus":"Inactive","jurisdiction":"New York, United States","entityTypeCategory":"CORPORATION"},{"entityName":"P.D.Q. AUTO SALES, INC.","dosID":"616827","initialFilingDate":"1980-03-25T00:00:00","county":"Bronx","nameType":"ACTUAL","assumedNameID":"","nonQualifiedID":"","assumedName":"","entityType":"DOMESTIC BUSINESS CORPORATION","entityStatus":"Inactive","jurisdiction":"New York, United States","entityTypeCategory":"CORPORATION"},{"entityName":"Q AUTO, LLC","dosID":"3375400","initialFilingDate":"2006-06-13T00:00:00","county":"Queens","nameType":"ACTUAL","assumedNameID":"","nonQualifiedID":"","assumedName":"","entityType":"DOMESTIC LIMITED LIABILITY COMPANY","entityStatus":"Inactive","jurisdiction":"New York, United States","entityTypeCategory":"LIMITED LIABILITY COMPANY"},{"entityName":"Q AUTO, LLC","dosID":"4885081","initialFilingDate":"2016-01-25T00:00:00","county":"Queens","nameType":"ACTUAL","assumedNameID":"","nonQualifiedID":"","assumedName":"","entityType":"DOMESTIC LIMITED LIABILITY COMPANY","entityStatus":"Active","jurisdiction":"New York, United States","entityTypeCategory":"LIMITED LIABILITY COMPANY"},{"entityName":"Q'S AUTO TRANSPORT INC.","dosID":"3461940","initialFilingDate":"2007-01-12T00:00:00","county":"Albany","nameType":"ACTUAL","assumedNameID":"","nonQualifiedID":"","assumedName":"","entityType":"DOMESTIC BUSINESS CORPORATION","entityStatus":"Inactive","jurisdiction":"New York, United States","entityTypeCategory":"CORPORATION"},{"entityName":"QAS USA LLC","dosID":"7304593","initialFilingDate":"2024-04-15T00:00:00","county":"Suffolk","nameType":"ACTUAL","assumedNameID":"","nonQualifiedID":"","assumedName":"","entityType":"DOMESTIC LIMITED LIABILITY COMPANY","entityStatus":"Active","jurisdiction":"New York, United States","entityTypeCategory":"LIMITED LIABILITY COMPANY"},{"entityName":"QAUCO PIPING AND HEATING, INC.","dosID":"1402708","initialFilingDate":"1989-11-27T00:00:00","county":"Queens","nameType":"ACTUAL","assumedNameID":"","nonQualifiedID":"","assumedName":"","entityType":"DOMESTIC BUSINESS CORPORATION","entityStatus":"Inactive","jurisdiction":"New York, United States","entityTypeCategory":"CORPORATION"},{"entityName":"QAULITTY RENTELZ LLC","dosID":"6626825","initialFilingDate":"2022-10-28T00:00:00","county":"Westchester","nameType":"ACTUAL","assumedNameID":"","nonQualifiedID":"","assumedName":"","entityType":"DOMESTIC LIMITED LIABILITY COMPANY","entityStatus":"Active","jurisdiction":"New York, United States","entityTypeCategory":"LIMITED LIABILITY COMPANY"},{"entityName":"QAULITY SERVICE LLC","dosID":"7187112","initialFilingDate":"2023-11-20T00:00:00","county":"Broome","nameType":"ACTUAL","assumedNameID":"","nonQualifiedID":"","assumedName":"","entityType":"DOMESTIC LIMITED LIABILITY COMPANY","entityStatus":"Active","jurisdiction":"New York, United States","entityTypeCategory":"LIMITED LIABILITY COMPANY"},{"entityName":"QAUNTUM FOODS INC.","dosID":"6805996","initialFilingDate":"2023-04-24T00:00:00","county":"Kings","nameType":"ACTUAL","assumedNameID":"","nonQualifiedID":"","assumedName":"","entityType":"DOMESTIC BUSINESS CORPORATION","entityStatus":"Active","jurisdiction":"New York, United States","entityTypeCategory":"CORPORATION"},{"entityName":"R.Q AUTO SALES CORP.","dosID":"2924084","initialFilingDate":"2003-06-26T00:00:00","county":"Kings","nameType":"ACTUAL","assumedNameID":"","nonQualifiedID":"","assumedName":"","entityType":"DOMESTIC BUSINESS CORPORATION","entityStatus":"Inactive","jurisdiction":"New York, United States","entityTypeCategory":"CORPORATION"},{"entityName":"T&Q AUTO INC.","dosID":"4977220","initialFilingDate":"2016-07-13T00:00:00","county":"Kings","nameType":"ACTUAL","assumedNameID":"","nonQualifiedID":"","assumedName":"","entityType":"DOMESTIC BUSINESS CORPORATION","entityStatus":"Inactive","jurisdiction":"New York, United States","entityTypeCategory":"CORPORATION"},{"entityName":"W & Q AUTO SERVICE INC.","dosID":"2484682","initialFilingDate":"2000-03-13T00:00:00","county":"Kings","nameType":"ACTUAL","assumedNameID":"","nonQualifiedID":"","assumedName":"","entityType":"DOMESTIC BUSINESS CORPORATION","entityStatus":"Inactive","jurisdiction":"New York, United States","entityTypeCategory":"CORPORATION"},{"entityName":"Y&Q AUTOTIRE INC.","dosID":"6992693","initialFilingDate":"2023-08-01T00:00:00","county":"Queens","nameType":"ACTUAL","assumedNameID":"","nonQualifiedID":"","assumedName":"","entityType":"DOMESTIC BUSINESS CORPORATION","entityStatus":"Active","jurisdiction":"New York, United States","entityTypeCategory":"CORPORATION"},{"entityName":"Z & Q AUTO GROUP INC.","dosID":"6707183","initialFilingDate":"2023-01-24T00:00:00","county":"Queens","nameType":"ACTUAL","assumedNameID":"","nonQualifiedID":"","assumedName":"","entityType":"DOMESTIC BUSINESS CORPORATION","entityStatus":"Active","jurisdiction":"New York, United States","entityTypeCategory":"CORPORATION"}],"totalMatchingCount":34}