{"transactionID":null,"timestamp":"2025-06-22T15:39:47.4645471-04:00","requestStatus":"Success","resultIndicator":"EntityMatchFound","entityGeneralInfo":{"entityName":"DA CAPO FUEL CELL COMPANY, LTD.","dosID":"2710413","foreignLegalName":"","fictitiousName":"","entityType":"DOMESTIC BUSINESS CORPORATION","durationDate":"","sectionofLaw":"402 BCL - BUSINESS CORPORATION LAW","entityStatus":"Inactive","dateOfInitialDosFiling":"2001-12-19T00:00:00","reasonForStatus":"","effectiveDateInitialFiling":"2001-12-19T00:00:00","inactiveDate":"2015-11-18T00:00:00","foreignFormationDate":"","statementStatus":"NOT REQUIRED","county":"Putnam","nextStatementDueDate":"2009-12-31T00:00:00","jurisdiction":"New York, United States","nfpCategory":""},"sopAddress":{"name":"C/O SATTERLEE STEPHENS BURKE & BURKE","address":{"streetAddress":"230 PARK AVE","streetAddress1":"230 PARK AVE","addressLine2":"STE 1130","streetAddress2":"STE 1130","city":"NEW YORK","state":"NY","zipCode":"10169","zipPlus4":"","country":"United States","countryCode":"USA"}},"electronicServiceOfProcessStatusId":null,"electronicServiceOfProcessStatusName":"Not Permitted","electronicServiceOfProcessEmail":null,"ceo":{"name":"FRANCIS H CABOT","address":{"streetAddress":"C/O SATTERLEE STEPHENS BURKE &","streetAddress1":"C/O SATTERLEE STEPHENS BURKE &","addressLine2":"BURKE, 230 PARK AVE, STE 1130","streetAddress2":"BURKE, 230 PARK AVE, STE 1130","city":"NEW YORK","state":"NY","zipCode":"10169","zipPlus4":"","country":"United States","countryCode":"USA"}},"locationAddress":{"name":null,"address":{"streetAddress":"","streetAddress1":"","addressLine2":"","streetAddress2":"","city":"","state":"  ","zipCode":"","zipPlus4":"","country":"","countryCode":""}},"poExecAddress":{"name":null,"address":{"streetAddress":"C/O SATTERLEE STEPHENS BURKE &","streetAddress1":"C/O SATTERLEE STEPHENS BURKE &","addressLine2":"BURKE, 230 PARK AVE, STE 1130","streetAddress2":"BURKE, 230 PARK AVE, STE 1130","city":"NEW YORK","state":"NY","zipCode":"10169","zipPlus4":"","country":"United States","countryCode":"USA"}},"registeredAgent":{"name":"","address":{"streetAddress":"","streetAddress1":"","addressLine2":"","streetAddress2":"","city":"","state":"  ","zipCode":"","zipPlus4":"","country":"","countryCode":""}},"farmCorpFlag":false,"stockShareInfoList":[{"corpID":3,"stockTypeDescriptor":"NO PAR VALUE","stockValue":"0.00000","quantity":"100"}],"latestDateDissolution":""}