{"transactionID":null,"timestamp":"2025-06-22T08:46:48.237867-04:00","requestStatus":"Success","resultIndicator":"EntityMatchFound","entityGeneralInfo":{"entityName":"PFIZER INTERNATIONAL INC.","dosID":"82981","foreignLegalName":"","fictitiousName":"","entityType":"DOMESTIC BUSINESS CORPORATION","durationDate":"","sectionofLaw":" - ","entityStatus":"Inactive","dateOfInitialDosFiling":"1951-12-18T00:00:00","reasonForStatus":"MERGED OUT OF EXISTENCE","effectiveDateInitialFiling":"1951-12-18T00:00:00","inactiveDate":"2003-03-13T00:00:00","foreignFormationDate":"","statementStatus":"NOT REQUIRED","county":"New York","nextStatementDueDate":"2003-12-31T00:00:00","jurisdiction":"New York, United States","nfpCategory":""},"sopAddress":{"name":"C/O C T CORPORATION SYSTEM","address":{"streetAddress":"111 EIGHTH AVENUE","streetAddress1":"111 EIGHTH AVENUE","addressLine2":"","streetAddress2":"","city":"NEW YORK","state":"NY","zipCode":"10011","zipPlus4":"","country":"United States","countryCode":"USA"}},"electronicServiceOfProcessStatusId":null,"electronicServiceOfProcessStatusName":"Not Permitted","electronicServiceOfProcessEmail":null,"ceo":{"name":"HENRY A MCKINNELL","address":{"streetAddress":"235 E 42ND ST","streetAddress1":"235 E 42ND ST","addressLine2":"","streetAddress2":"","city":"NEW YORK","state":"NY","zipCode":"10017","zipPlus4":"5755","country":"United States","countryCode":"USA"}},"locationAddress":{"name":null,"address":{"streetAddress":"","streetAddress1":"","addressLine2":"","streetAddress2":"","city":"","state":"  ","zipCode":"","zipPlus4":"","country":"","countryCode":""}},"poExecAddress":{"name":null,"address":{"streetAddress":"235 E. 42 ST.","streetAddress1":"235 E. 42 ST.","addressLine2":"","streetAddress2":"","city":"NEW YORK","state":"NY","zipCode":"10017","zipPlus4":"5755","country":"United States","countryCode":"USA"}},"registeredAgent":{"name":"C T CORPORATION SYSTEM","address":{"streetAddress":"111 EIGHTH AVENUE","streetAddress1":"111 EIGHTH AVENUE","addressLine2":"","streetAddress2":"","city":"NEW YORK","state":"NY","zipCode":"10011","zipPlus4":"","country":"","countryCode":"USA"}},"farmCorpFlag":false,"stockShareInfoList":[{"corpID":4,"stockTypeDescriptor":"PAR VALUE","stockValue":"0.01000","quantity":"1000000"},{"corpID":4,"stockTypeDescriptor":"PAR VALUE","stockValue":"0.20000","quantity":"2400000"}],"latestDateDissolution":""}