{"transactionID":null,"timestamp":"2025-06-22T02:10:18.4346606-04:00","requestStatus":"Success","resultIndicator":"EntityMatchFound","entityGeneralInfo":{"entityName":"AMERICAN WOOLS PTY LTD.","dosID":"3631960","foreignLegalName":"","fictitiousName":"","entityType":"DOMESTIC BUSINESS CORPORATION","durationDate":"","sectionofLaw":"402 BCL - BUSINESS CORPORATION LAW","entityStatus":"Active","dateOfInitialDosFiling":"2008-02-14T00:00:00","reasonForStatus":"","effectiveDateInitialFiling":"2008-02-14T00:00:00","inactiveDate":"","foreignFormationDate":"","statementStatus":"PAST DUE DATE","county":"Queens","nextStatementDueDate":"2014-02-28T00:00:00","jurisdiction":"New York, United States","nfpCategory":""},"sopAddress":{"name":"AMERICAN WOOLS PTY LTD.","address":{"streetAddress":"40 NEWPORT PARKWAY","streetAddress1":"40 NEWPORT PARKWAY","addressLine2":"","streetAddress2":"","city":"JERESY CITY","state":"NJ","zipCode":"07310","zipPlus4":"","country":"United States","countryCode":"USA"}},"electronicServiceOfProcessStatusId":null,"electronicServiceOfProcessStatusName":"Not Permitted","electronicServiceOfProcessEmail":null,"ceo":{"name":"AMIT AGGARWAL","address":{"streetAddress":"40 NEWPORT PARKWAY","streetAddress1":"40 NEWPORT PARKWAY","addressLine2":"APT 708","streetAddress2":"APT 708","city":"JERESY CITY","state":"NJ","zipCode":"07310","zipPlus4":"","country":"United States","countryCode":"USA"}},"locationAddress":{"name":null,"address":{"streetAddress":"","streetAddress1":"","addressLine2":"","streetAddress2":"","city":"","state":"  ","zipCode":"","zipPlus4":"","country":"","countryCode":""}},"poExecAddress":{"name":null,"address":{"streetAddress":"40 NEWPORT PARKWAY","streetAddress1":"40 NEWPORT PARKWAY","addressLine2":"","streetAddress2":"","city":"JERESY CITY","state":"NJ","zipCode":"07310","zipPlus4":"","country":"United States","countryCode":"USA"}},"registeredAgent":{"name":"","address":{"streetAddress":"","streetAddress1":"","addressLine2":"","streetAddress2":"","city":"","state":"  ","zipCode":"","zipPlus4":"","country":"","countryCode":""}},"farmCorpFlag":false,"stockShareInfoList":[{"corpID":3,"stockTypeDescriptor":"NO PAR VALUE","stockValue":"0.00000","quantity":"200"}],"latestDateDissolution":""}