{"transactionID":null,"timestamp":"2025-06-21T22:32:16.7365555-04:00","requestStatus":"Success","resultIndicator":"EntityMatchFound","entityGeneralInfo":{"entityName":"M & D SPEECH SERVICES INC","dosID":"3703250","foreignLegalName":"","fictitiousName":"","entityType":"DOMESTIC BUSINESS CORPORATION","durationDate":"","sectionofLaw":"402 BCL - BUSINESS CORPORATION LAW","entityStatus":"Active","dateOfInitialDosFiling":"2008-07-31T00:00:00","reasonForStatus":"","effectiveDateInitialFiling":"2008-07-31T00:00:00","inactiveDate":"","foreignFormationDate":"","statementStatus":"PAST DUE DATE","county":"Queens","nextStatementDueDate":"2014-07-31T00:00:00","jurisdiction":"New York, United States","nfpCategory":""},"sopAddress":{"name":"THE CORPORATION","address":{"streetAddress":"6339 DRY HARBOR ROAD","streetAddress1":"6339 DRY HARBOR ROAD","addressLine2":"","streetAddress2":"","city":"MIDDLE VILLAGE","state":"NY","zipCode":"11379","zipPlus4":"","country":"United States","countryCode":"USA"}},"electronicServiceOfProcessStatusId":null,"electronicServiceOfProcessStatusName":"Not Permitted","electronicServiceOfProcessEmail":null,"ceo":{"name":"JULIA HILKEVICH","address":{"streetAddress":"6339 DRY HARBOR RD","streetAddress1":"6339 DRY HARBOR RD","addressLine2":"","streetAddress2":"","city":"MIDDLE VILLAGE","state":"NY","zipCode":"11379","zipPlus4":"","country":"United States","countryCode":"USA"}},"locationAddress":{"name":null,"address":{"streetAddress":"","streetAddress1":"","addressLine2":"","streetAddress2":"","city":"","state":"  ","zipCode":"","zipPlus4":"","country":"","countryCode":""}},"poExecAddress":{"name":null,"address":{"streetAddress":"6339 DRY HARBOR RD","streetAddress1":"6339 DRY HARBOR RD","addressLine2":"","streetAddress2":"","city":"MIDDLE VILLAGE","state":"NY","zipCode":"11379","zipPlus4":"","country":"United States","countryCode":"USA"}},"registeredAgent":{"name":"TOM ROMANO","address":{"streetAddress":"C/O NYSCORPORATION.COM","streetAddress1":"C/O NYSCORPORATION.COM","addressLine2":"228 PARK AVENUE SOUTH, #6165","streetAddress2":"228 PARK AVENUE SOUTH, #6165","city":"NEW YORK","state":"NY","zipCode":"10003","zipPlus4":"","country":"","countryCode":"USA"}},"farmCorpFlag":false,"stockShareInfoList":[{"corpID":3,"stockTypeDescriptor":"NO PAR VALUE","stockValue":"0.00000","quantity":"200"}],"latestDateDissolution":""}