{"transactionID":null,"timestamp":"0001-01-01T00:00:00","requestStatus":"Success","resultIndicator":"EntityMatchFound","entityGeneralInfo":{"entityName":"CORDIUM US HOLDCO, INC.","dosID":"4894190","foreignLegalName":"","fictitiousName":"","entityType":"FOREIGN BUSINESS CORPORATION","durationDate":"","sectionofLaw":"1304 BCL - BUSINESS CORPORATION LAW","entityStatus":"Inactive","dateOfInitialDosFiling":"2016-02-10T00:00:00","reasonForStatus":"Terminated","effectiveDateInitialFiling":"2016-02-10T00:00:00","inactiveDate":"2020-02-28T00:00:00","foreignFormationDate":"2015-03-06T00:00:00","statementStatus":"NOT REQUIRED","county":"New York","nextStatementDueDate":"2020-02-29T00:00:00","jurisdiction":"Delaware, United States","nfpCategory":""},"sopAddress":{"name":"CORPORATION SERVICE COMPANY","address":{"streetAddress":"80 STATE ST","streetAddress1":"80 STATE ST","addressLine2":"","streetAddress2":"","city":"ALBANY","state":"NY","zipCode":"12207","zipPlus4":"2543","country":"United States","countryCode":"USA"}},"electronicServiceOfProcessStatusId":null,"electronicServiceOfProcessStatusName":"Not Permitted","electronicServiceOfProcessEmail":null,"ceo":{"name":"DOUG MORGAN","address":{"streetAddress":"140 EAST 45TH STREET","streetAddress1":"140 EAST 45TH STREET","addressLine2":"29TH FLOOR","streetAddress2":"29TH FLOOR","city":"NEW YORK","state":"NY","zipCode":"10017","zipPlus4":"","country":"United States","countryCode":"USA"}},"locationAddress":{"name":null,"address":{"streetAddress":"","streetAddress1":"","addressLine2":"","streetAddress2":"","city":"","state":"  ","zipCode":"","zipPlus4":"","country":"","countryCode":""}},"poExecAddress":{"name":null,"address":{"streetAddress":"140 EAST 45TH STREET","streetAddress1":"140 EAST 45TH STREET","addressLine2":"29TH FLOOR","streetAddress2":"29TH FLOOR","city":"NEW YORK","state":"NY","zipCode":"10017","zipPlus4":"","country":"United States","countryCode":"USA"}},"registeredAgent":{"name":"REGISTERED AGENT REVOKED","address":{"streetAddress":"","streetAddress1":"","addressLine2":"","streetAddress2":"","city":"","state":"  ","zipCode":"","zipPlus4":"","country":"","countryCode":""}},"farmCorpFlag":false,"stockShareInfoList":null,"latestDateDissolution":""}