{"transactionID":null,"timestamp":"0001-01-01T00:00:00","requestStatus":"Success","resultIndicator":"EntityMatchFound","entityGeneralInfo":{"entityName":"OMNI AGENT SOLUTIONS INC.","dosID":"4175516","foreignLegalName":"","fictitiousName":"","entityType":"FOREIGN BUSINESS CORPORATION","durationDate":"","sectionofLaw":"1304 BCL - BUSINESS CORPORATION LAW","entityStatus":"Active","dateOfInitialDosFiling":"2011-12-12T00:00:00","reasonForStatus":"","effectiveDateInitialFiling":"2011-12-12T00:00:00","inactiveDate":"","foreignFormationDate":"2011-12-07T00:00:00","statementStatus":"CURRENT","county":"Albany","nextStatementDueDate":"2025-12-31T00:00:00","jurisdiction":"Delaware, United States","nfpCategory":""},"sopAddress":{"name":"VCORP AGENT SERVICES, INC.","address":{"streetAddress":"25 ROBERT PITT DRIVE","streetAddress1":"25 ROBERT PITT DRIVE","addressLine2":"SUITE 204","streetAddress2":"SUITE 204","city":"MONSEY","state":"NY","zipCode":"10952","zipPlus4":"","country":"United States","countryCode":"USA"}},"electronicServiceOfProcessStatusId":null,"electronicServiceOfProcessStatusName":"Not Permitted","electronicServiceOfProcessEmail":null,"ceo":{"name":"BRIAN OSBORNE","address":{"streetAddress":"5955 DE SOTO AVE","streetAddress1":"5955 DE SOTO AVE","addressLine2":"SUITE 100","streetAddress2":"SUITE 100","city":"WOODLAND HILLS","state":"CA","zipCode":"91367","zipPlus4":"","country":"United States","countryCode":"USA"}},"locationAddress":{"name":null,"address":{"streetAddress":"","streetAddress1":"","addressLine2":"","streetAddress2":"","city":"","state":"  ","zipCode":"","zipPlus4":"","country":"","countryCode":""}},"poExecAddress":{"name":null,"address":{"streetAddress":"5955 DE SOTO AVE","streetAddress1":"5955 DE SOTO AVE","addressLine2":"","streetAddress2":"","city":"WOODLAND HILLS","state":"CA","zipCode":"91367","zipPlus4":"","country":"United States","countryCode":"USA"}},"registeredAgent":{"name":"","address":{"streetAddress":"","streetAddress1":"","addressLine2":"","streetAddress2":"","city":"","state":"  ","zipCode":"","zipPlus4":"","country":"","countryCode":""}},"farmCorpFlag":false,"stockShareInfoList":null,"latestDateDissolution":""}