{"transactionID":null,"timestamp":"2025-06-22T04:06:25.9294956-04:00","requestStatus":"Success","resultIndicator":"EntityMatchFound","entityGeneralInfo":{"entityName":"J & S DRAPERY, INC.","dosID":"2022534","foreignLegalName":"","fictitiousName":"","entityType":"DOMESTIC BUSINESS CORPORATION","durationDate":"","sectionofLaw":"402 BCL - BUSINESS CORPORATION LAW","entityStatus":"Active","dateOfInitialDosFiling":"1996-04-23T00:00:00","reasonForStatus":"","effectiveDateInitialFiling":"1996-04-23T00:00:00","inactiveDate":"","foreignFormationDate":"","statementStatus":"PAST DUE DATE","county":"Onondaga","nextStatementDueDate":"2016-04-30T00:00:00","jurisdiction":"New York, United States","nfpCategory":""},"sopAddress":{"name":"THE CORPORATION","address":{"streetAddress":"131 W SENECA ST","streetAddress1":"131 W SENECA ST","addressLine2":"","streetAddress2":"","city":"MANLIUS","state":"NY","zipCode":"13104","zipPlus4":"","country":"United States","countryCode":"USA"}},"electronicServiceOfProcessStatusId":null,"electronicServiceOfProcessStatusName":"Not Permitted","electronicServiceOfProcessEmail":null,"ceo":{"name":"JEFFREY A SOLOMON","address":{"streetAddress":"131 W SENECA ST","streetAddress1":"131 W SENECA ST","addressLine2":"","streetAddress2":"","city":"MANLIUS","state":"NY","zipCode":"13104","zipPlus4":"","country":"United States","countryCode":"USA"}},"locationAddress":{"name":null,"address":{"streetAddress":"","streetAddress1":"","addressLine2":"","streetAddress2":"","city":"","state":"  ","zipCode":"","zipPlus4":"","country":"","countryCode":""}},"poExecAddress":{"name":null,"address":{"streetAddress":"131 W SENECA ST","streetAddress1":"131 W SENECA ST","addressLine2":"","streetAddress2":"","city":"MANLIUS","state":"NY","zipCode":"13104","zipPlus4":"","country":"United States","countryCode":"USA"}},"registeredAgent":{"name":"","address":{"streetAddress":"","streetAddress1":"","addressLine2":"","streetAddress2":"","city":"","state":"  ","zipCode":"","zipPlus4":"","country":"","countryCode":""}},"farmCorpFlag":false,"stockShareInfoList":[{"corpID":3,"stockTypeDescriptor":"NO PAR VALUE","stockValue":"0.00000","quantity":"200"}],"latestDateDissolution":""}